functricks/__init__.py
functricks/_core/__init__.py
functricks/_core/keyalias.py
functricks/_core/overloadable.py
functricks/_core/tofunc.py
functricks/tests/__init__.py
functricks/tests/test_legacy.py
functricks-1.0.1.dist-info/LICENSE.txt
functricks-1.0.1.dist-info/METADATA
functricks-1.0.1.dist-info/WHEEL
functricks-1.0.1.dist-info/top_level.txt
functricks-1.0.1.dist-info/RECORD
