Metadata-Version: 2.1
Name: functricks
Version: 1.0.1
Summary: Uniting some function utilities inside of one project.
Author-email: Johannes <johannes-programming@mailfence.com>
License: The MIT License (MIT)
Project-URL: Documentation, https://pypi.org/project/functricks
Project-URL: Download, https://pypi.org/project/functricks/#files
Project-URL: Source, https://github.com/johannes-programming/functricks
Classifier: Intended Audience :: Developers
Classifier: License :: OSI Approved :: MIT License
Classifier: Programming Language :: Python
Classifier: Programming Language :: Python :: 3
Classifier: Programming Language :: Python :: 3 :: Only
Requires-Python: >=3.10
License-File: LICENSE.txt
